<Groups><Pool id="12299232@N00" title="image manipulations - please comment other pix"/><Pool id="15166189@N00" title="The Photographer's Club"/><Pool id="16141209@N00" title="Emotions"/><Pool id="26058684@N00" title="Amateur Digital Photography/Help and Ideas"/><Pool id="28747776@N00" title="Colors of the World"/><Pool id="29496069@N00" title="Portraiture Photography"/><Pool id="30042135@N00" title="Autoportrait"/><Pool id="32002189@N00" title="Experimental Dream"/><Pool id="35034354591@N01" title="DeviantArt"/><Pool id="35034364564@N01" title="Nikon Digital"/><Pool id="35237103229@N01" title="Español"/><Pool id="35468145766@N01" title="Models"/><Pool id="37996574841@N01" title="ART DISTRICT"/><Pool id="37996655186@N01" title="Spain"/><Pool id="40732569271@N01" title="Photography"/><Pool id="41476112@N00" title="Nikon"/><Pool id="42569370@N00" title="internet artists gallery"/><Pool id="44124366823@N01" title="deviantART Deviants"/><Pool id="49503026089@N01" title="StreetPhoto"/><Pool id="51035548158@N01" title="UK Flickr users"/><Pool id="51035577168@N01" title="日本語flick'r"/><Pool id="52240076981@N01" title="Happy!"/><Pool id="52240315905@N01" title="YayHooray!"/><Pool id="52240540038@N01" title="Zona libre"/><Pool id="52240944201@N01" title="People Portraits"/><Pool id="52241529856@N01" title="日本語を使うぞ〜"/><Pool id="52447432@N00" title="Lights and Shadows"/><Pool id="54739042@N00" title="Your camera collection !"/><Pool id="58898522@N00" title="Artistic Photography"/><Pool id="64332025@N00" title="FASHION PHOTOGRAPHY"/><Pool id="76535076@N00" title="Flickr Addicts"/><Pool id="80311671@N00" title="~ EyEs ~"/><Pool id="81069933@N00" title="Global Photojournalism"/><Pool id="82449190@N00" title="フリッカー"/><Pool id="85334335@N00" title="The Light Fantastic"/><Pool id="68567710@N00" title="Your &quot;Postcard&quot; Shot"/><Pool id="70063023@N00" title="白黒写真"/><Pool id="19477613@N00" title="raw photography"/><Pool id="30649887@N00" title="AMaZiNG"/><Pool id="70823775@N00" title="All People"/><Pool id="21819324@N00" title="People of the World"/><Pool id="43116471@N00" title="Young Photographers"/><Pool id="15153247@N00" title="!FlickrSoup for Soul"/><Pool id="43501458@N00" title="Amateurs"/><Pool id="39427645@N00" title="Creative"/><Pool id="88148454@N00" title="I am..."/><Pool id="32625837@N00" title="#flickr"/><Pool id="11488522@N00" title="visit the world - the travel guide"/><Pool id="18789265@N00" title="Black, White and Colour"/><Pool id="48721108@N00" title="Photos Around The World"/><Pool id="58286952@N00" title="Your Favorite Photos - Unlimited!"/><Pool id="58021845@N00" title="GirlsWithAttitude"/><Pool id="78841270@N00" title="Conceptual photography"/><Pool id="13536067@N00" title="Nikon World"/><Pool id="95309787@N00" title="Flickritis: Where 45,415people are still happily infected!"/><Pool id="11512103@N00" title="100 Club (All pics must have been 'Favorited' at least 100 times"/><Pool id="83435940@N00" title="1000 Views"/><Pool id="57998059@N00" title="I love FOTOGRAFIA"/><Pool id="81431815@N00" title="FLICKR NATURE"/><Pool id="94275711@N00" title="Photography Corner"/><Pool id="53533007@N00" title="****Every picture tells a story****"/><Pool id="94076755@N00" title="T H E C L I C K - UNLIMITED"/><Pool id="95702907@N00" title="1500 views"/><Pool id="74729440@N00" title="Nikon Digital Magic"/><Pool id="62334926@N00" title="Nikon Digital SLRs"/><Pool id="94253929@N00" title="This"/><Pool id="73162739@N00" title="400 views"/><Pool id="38195989@N00" title="without rules"/><Pool id="43411191@N00" title="Beautiful People"/><Pool id="96902893@N00" title="Full of colors"/><Pool id="34818690@N00" title="VOGUE"/><Pool id="74503698@N00" title="AMAZING: commented with amazing"/><Pool id="28795624@N00" title="100 faves"/><Pool id="67116847@N00" title="Street Art on Flickr"/><Pool id="24861035@N00" title="My best"/><Pool id="57712356@N00" title="Moments in life..."/><Pool id="84838893@N00" title="影像日记"/><Pool id="11616304@N00" title="中途半端な写真好き☆"/><Pool id="76649513@N00" title="ANYTHING ALLOWED!!!!!!"/><Pool id="87808104@N00" title="Amateur Photographers"/><Pool id="44575233@N00" title="100 Favorites"/><Pool id="70952230@N00" title="I love Flickr!"/><Pool id="64916869@N00" title="Your photo goes here!"/><Pool id="72289549@N00" title="Portraits... Get Closer!"/><Pool id="20933295@N00" title="Poetic Photography"/><Pool id="32266655@N00" title="Views: 500"/><Pool id="37045109@N00" title="Views: 100"/><Pool id="35419517@N00" title="Views: 200"/><Pool id="85342170@N00" title="Views: 1000"/><Pool id="88055075@N00" title="Life is Art!"/><Pool id="68555142@N00" title="Nikon Lenses users"/><Pool id="79419660@N00" title="Cinematic Photography"/><Pool id="71902092@N00" title="Nikonians"/><Pool id="33036762@N00" title="Anything Goes No Limits"/><Pool id="69962899@N00" title="NIKON Gears"/><Pool id="44397493@N00" title="Flickr clickr"/><Pool id="29786937@N00" title="Views 4000"/><Pool id="77078651@N00" title="* Travel Photography for World Nomads *"/><Pool id="83561758@N00" title="Very Beautiful Women"/><Pool id="79406843@N00" title="fine-art"/><Pool id="88434829@N00" title="$how me the money--post your most viewed pic--300 views minumum"/><Pool id="18655067@N00" title="Domino Magazine"/><Pool id="66882717@N00" title="Girona"/><Pool id="16008993@N00" title="Beautiful Views"/><Pool id="14512440@N00" title="CentralFlickr"/><Pool id="35974286@N00" title="50 faves"/><Pool id="42815942@N00" title="**El fotógrafo satisfecho//The satisfied photographer"/><Pool id="95319459@N00" title="*Really Unlimited*"/><Pool id="11427634@N00" title="*Inspirational Travel Photos"/><Pool id="33196684@N00" title="Girona Provincia"/><Pool id="96038738@N00" title="Adobe Masters"/><Pool id="56046101@N00" title="Adoring her ..."/><Pool id="20759249@N00" title="10 Million Photos"/><Pool id="74794523@N00" title="TRAVEL Photography!"/><Pool id="33968254@N00" title="! ANYTHING &amp; EVERYTHING ! 142,977 photos &amp; 1,423 members &amp; count"/><Pool id="93994529@N00" title="* 20 COMMENTS and up"/><Pool id="57122062@N00" title="Aspiring Young Photographers"/><Pool id="59789927@N00" title="Photoshop Professionals"/><Pool id="84223821@N00" title="Nikon photos"/><Pool id="55967416@N00" title="Amazing!!!"/><Pool id="42827898@N00" title="Photos with 1000 views (and more)"/><Pool id="21441943@N00" title="minimum 1000 views"/><Pool id="78934823@N00" title="minimum 2000 views"/><Pool id="97065465@N00" title="Magazine Art"/><Pool id="64468370@N00" title="U_MAG"/><Pool id="66036618@N00" title="Flickr VOGUE"/><Pool id="79742675@N00" title="minimum 1500 views"/><Pool id="83266896@N00" title="Joves Catalans"/><Pool id="25602472@N00" title="rhizom magazine"/><Pool id="62335151@N00" title="Linux Flickrs"/><Pool id="22086684@N00" title="Nikon Cafe"/><Pool id="40551728@N00" title="Pixel Peeper"/><Pool id="24772180@N00" title="1 day we'll have the most photos on Flickr"/><Pool id="49287201@N00" title="VirusPhoto"/><Pool id="10681612@N00" title="All interesting shots- NO RULES!!!!!!!!!!!!"/><Pool id="93235184@N00" title="Adorn Magazine"/><Pool id="32613242@N00" title="~600 to 700~"/><Pool id="92632932@N00" title="Nylon Magazine"/><Pool id="42425890@N00" title="Nikkor on Canon"/><Pool id="89572171@N00" title="Fotográfos Apasionados, PHOTOGRAPHY LOVER'S (All World)"/><Pool id="328452@N20" title="WORLD PICTURE / Challenge and Award"/><Pool id="354296@N21" title="[todo] ESPAÑA."/><Pool id="309108@N25" title="Get noticed"/><Pool id="357533@N21" title="カメラ日和"/><Pool id="378552@N21" title="NO Rules! Seattle"/><Pool id="408125@N22" title="Young Minds"/><Pool id="365613@N20" title="Lightroom + Photoshop"/><Pool id="400380@N21" title="No Flickr censorship!"/><Pool id="386293@N20" title="i-D Magazine"/><Pool id="396220@N20" title="A Vista de Objetivo"/><Pool id="432968@N23" title="Flickrmania"/><Pool id="410300@N25" title="Your Visions"/><Pool id="496554@N25" title="*fotos simples/ simple photos* ( post all,comment on 1)"/><Pool id="513921@N24" title="Dragon Gold Award &quot; The Best Of Flickr &quot;"/><Pool id="587639@N22" title="The way I notice this world"/><Pool id="548459@N20" title="Photographes &amp; modeles"/><Pool id="609463@N22" title="She-Beauty"/><Pool id="615270@N22" title="&quot;Unlimited Photos: No Rules&quot;"/><Pool id="629141@N22" title="Foro Nikonistas.com"/><Pool id="633236@N22" title="Just Amazing Photos"/><Pool id="642220@N22" title="FOTOGRAFOS &amp; MODELOS / PHOTOGRAPHERS &amp; MODELS"/><Pool id="568088@N25" title="Canon vs Nikon"/><Pool id="570164@N25" title="Fotografe uma Ideia!"/><Pool id="608847@N20" title="paper + wire magazine"/><Pool id="615955@N24" title="Photography Magazine, I Heart"/><Pool id="684830@N22" title="Fine Art Photography (in the footsteps of the masters)"/><Pool id="670621@N23" title="Amateur Digital Photography Group"/><Pool id="714094@N22" title=":: Retratos femeninos"/><Pool id="658863@N24" title="INDIE AND ALTERNATIVE FASHION PHOTOGRAPHY"/><Pool id="720102@N23" title="1,000,000"/><Pool id="768751@N23" title="Women Women Women"/><Pool id="746649@N24" title="Glamour Photography"/><Pool id="736342@N25" title="The Official Digital Camera Magazine Flickr Group"/><Pool id="763172@N20" title="LULA Magazine"/><Pool id="797676@N23" title="PhotoZone"/><Pool id="803732@N21" title="Digital Photography Review"/><Pool id="759181@N25" title="The Nikon FX Group"/><Pool id="854588@N23" title="VINTAGE-LOOKING photography."/><Pool id="870616@N20" title="PEOPLE_OF_ THE_WORLD"/><Pool id="924487@N22" title="Nikon Club Community"/><Pool id="916244@N23" title="Fotògrafs Catalans"/><Pool id="867256@N25" title="Bokeh Masters"/><Pool id="947377@N22" title="∆∆∆∆∆∆∆∆∆∆∆∆∆∆∆∆∆∆∆∆∆"/><Pool id="936066@N23" title="Amazing Shot"/><Pool id="899189@N24" title="100.000.000 Flickr Photos"/><Pool id="962532@N23" title="young and inspired"/><Pool id="964511@N23" title="PLATEFORM magazine"/><Pool id="927402@N24" title="New photographers of all around the world"/><Pool id="1005601@N22" title="Model Maze Magazine"/><Pool id="954524@N24" title="! Flickr Cafe !"/><Pool id="946859@N25" title="Yes, i'm a dreamer."/><Pool id="948970@N25" title="&quot;LO VEO, ME GUSTA, ME INTERESA, LO FOTOGRAFÍO&quot;"/><Pool id="1007335@N23" title="all cool pictures"/><Pool id="1013568@N23" title="Digitalphotos Magazine-Publish your photo!"/><Pool id="1042590@N22" title="all digital"/><Pool id="1032085@N21" title="POTPOURRI MAGAZINE"/><Pool id="1038674@N23" title="Foto DNG magazine"/><Pool id="1051871@N23" title="INK MAGAZINE"/><Pool id="1007988@N25" title="you are awesome"/><Pool id="1037228@N20" title="just cool pictures"/><Pool id="1074693@N23" title="! The Flickr !"/><Pool id="1082093@N21" title="We Love lightroom"/><Pool id="1047239@N25" title="Awesome:)"/><Pool id="1139076@N22" title="*poetry of images"/><Pool id="1115787@N21" title="Digitalphotos Magazine"/><Pool id="1150931@N22" title="Ilovethatphoto.net Photography Magazine"/><Pool id="1088749@N24" title="anything may go"/><Pool id="1136445@N23" title="Depth of Field Shots (NO LIMIT)"/><Pool id="1100655@N24" title="RazorMonkey Magazine"/><Pool id="1238753@N22" title="4Cosplay Magazine"/><Pool id="1248916@N23" title="PhotoGrafArtè"/><Pool id="1223452@N25" title="burn magazine"/><Pool id="1249327@N24" title="!Portfolio of People (HIGH QUALITY, ADMIN MODERATED p1/c2)"/><Pool id="1259926@N24" title="Nikon D7000 Users Group"/><Pool id="1336198@N22" title="Camera Nuts"/><Pool id="1276118@N24" title="* Open *"/><Pool id="1378208@N22" title="Your best creation"/><Pool id="1304178@N25" title="Ilovefake Magazine"/><Pool id="1356078@N21" title="Nikon D7000"/><Pool id="1415923@N22" title="School of Digital Photography"/><Pool id="1389321@N21" title="1 billion photos"/><Pool id="1380224@N20" title="Vice FR flickr"/><Pool id="1388054@N24" title="The D-Photo"/><Pool id="1429901@N21" title="★★Les Teves Millors Imatges/Your Best Pictures★★"/><Pool id="1449474@N21" title="FINE Magazine - Photographer Search"/><Pool id="1479373@N22" title="SHEER MAGAZINE"/><Pool id="1428211@N24" title="***FOTOGRAFIA EMOCION ♥ EMOTIONAL PHOTOGRAPHY***"/><Pool id="1449596@N20" title="Modern Vintage Photography"/><Pool id="1437396@N25" title="CRAP Magazine Search for Talent"/><Pool id="1496911@N23" title="ThePhoblographer"/><Pool id="1468619@N20" title="Nikon  D7000"/><Pool id="1505334@N21" title="Nikon D7000 Guild"/><Pool id="1511617@N21" title="Nikon D7000 Members"/><Pool id="1516558@N21" title="NIKON D7000 CAFE"/><Pool id="1507018@N25" title="Zona Kreativa"/><Pool id="1563512@N21" title="Nikon D7000 UK users"/><Pool id="1538497@N24" title="Union of Free Photographers"/><Pool id="1537572@N25" title="HAPPY CAMPER MAGAZINE"/><Pool id="1555525@N25" title="IHC on Flickr"/><Pool id="1607664@N21" title="Publickr Flickr"/><Pool id="1641117@N23" title="Starry Night Astrophotography"/><Pool id="1642531@N23" title="Portraits of women (woman only)"/><Pool id="1603394@N24" title="PhotoDonuts"/><Pool id="1693936@N22" title="Phlearn"/><Pool id="1672998@N23" title="beautiful portrait"/><Pool id="1631667@N24" title="Daniel's Pic Pocket"/><Pool id="1623479@N25" title="♦♦♦ IMMAGINI  -  FOTO -  SENTIMENTI  ♦♦♦"/><Pool id="1624189@N25" title="Anything You're Proud Of!!"/><Pool id="1704225@N22" title="The Magnificent Photos"/><Pool id="1739751@N22" title="Photoplus"/><Pool id="1739588@N21" title="Novel Magazine"/><Pool id="1706847@N24" title="100 MILLION PHOTOS !!!!!"/><Pool id="1707319@N25" title="PFB Magazine"/><Pool id="1775667@N21" title="♦♦♦ PHOTO VERY NICE ♦♦♦"/><Pool id="1753147@N20" title="Fotògrafs Gironins"/><Pool id="1746793@N24" title="JPeople Magazine"/><Pool id="1755894@N24" title="Creative shooters"/><Pool id="1834436@N22" title="iCapture"/><Pool id="1787560@N20" title="Photos - All you want"/><Pool id="1820068@N23" title="Журнал Фотомастерская/Photoworkshop magazine"/><Pool id="1825769@N21" title="Inviting Images"/><Pool id="1861154@N22" title="Your Best Shot For Today"/><Pool id="1789665@N25" title="Nikon Photographs"/><Pool id="1814766@N24" title="We love it !"/><Pool id="1892494@N23" title="PLYM Magazine"/><Pool id="1857442@N24" title="Only images and picture quality  - P1 /C2"/><Pool id="1872484@N24" title="Digital Camera World"/><Pool id="1927547@N23" title="1 Quadrillion Pix"/><Pool id="2069653@N22" title="Sarmad Magazine"/><Pool id="2048361@N23" title="Photography Week"/><Pool id="2138658@N22" title="flickr clickx"/><Pool id="2186597@N22" title="Faces Of The Universe"/><Pool id="2144894@N25" title="Dreams Magazine"/><Pool id="2185216@N20" title="World Photographers' Photos"/><Pool id="2196947@N20" title="Digital SLR Life™"/><Pool id="2256893@N22" title="Nikon DSLR Photographers"/><Pool id="2260589@N23" title="Aspiring Stock Photographers"/><Pool id="2232426@N20" title="Sube lo que quieras / Up what you want"/><Pool id="2218487@N25" title="Amaze me please"/><Pool id="2278698@N23" title="100 Views Unlimited"/><Pool id="2280875@N23" title="Flickr-eyes"/><Pool id="2236837@N25" title="Flickr cola فليكر كولا"/><Pool id="2288595@N21" title="CanonTURK Flickr Grubu"/><Pool id="2305855@N23" title="Digital Photo Mag"/><Pool id="2331163@N25" title="My flickr's friends' photos"/><Pool id="2336096@N25" title="1,000 Views Unlimited 1000"/><Pool id="2341915@N25" title="400 Views Unlimited"/><Pool id="2419720@N22" title="Photo Digital Club"/><Pool id="2352995@N25" title="Absolute Quality Gallery"/><Pool id="2415370@N21" title="Portfolio Explore"/><Pool id="2513089@N22" title="IG Photographers"/><Pool id="2509039@N23" title="Your best of the best"/><Pool id="2516269@N21" title="Photo's passion of the world"/><Pool id="2486584@N25" title="The Whattaroll Magazine Motion Issue Submissions Pool"/><Pool id="2597988@N22" title="Rewind Magazine"/><Pool id="2582107@N21" title="ORIGINAL PHOTO"/><Pool id="2600150@N20" title="㋡ flicker ○● DEPOT ㋡"/><Pool id="2609558@N20" title="阿刘摄影研究会"/><Pool id="2681791@N22" title="Catalans al mon"/><Pool id="2692194@N22" title="! ALL ARE WELCOME !"/><Pool id="2649225@N24" title="Photographies du monde"/><Pool id="2663354@N24" title="Flesh &amp; Bone Magazine"/><Pool id="2707874@N23" title="Flickr Unlimited - No Rules, No Limits"/><Pool id="2717776@N23" title="Free Expression Photography"/><Pool id="2669832@N25" title="Flickr Community–Around the world"/><Pool id="2671271@N25" title="&quot;Exploration of Surrealism,Nature,Abstract,What Comes In Mind&quot;"/><Pool id="2694310@N20" title="Life and moments ^_^"/><Pool id="2680219@N25" title="fotografos por la paz y el arte"/><Pool id="2705113@N20" title="Nikonistas de todo el mundo/Nikonists from all the world"/><Pool id="2732009@N21" title="Top Photography..."/><Pool id="2724778@N20" title="my best photographs and others who believe they are yours.Mis me"/><Pool id="2728886@N20" title="! Flickr All Stars !"/><Pool id="2721477@N24" title="fotografia sem limites unlimited photo"/><Pool id="2790762@N22" title="My Camera Tells All"/><Pool id="2748982@N20" title="all photos for all"/><Pool id="2727882@N25" title=".:CreativeMinds:."/><Pool id="2739342@N24" title="post any photo"/><Pool id="2732412@N25" title="Nikon is my passion"/><Pool id="2821817@N22" title="Nikon fixed focal lengths"/><Pool id="2780623@N20" title="EXPLORE OF THE WORK"/><Pool id="2840086@N22" title="Flickr Flooders"/></Groups>
